seagrass/__init__.py
seagrass/_docs.py
seagrass/_logging.py
seagrass/_typing.py
seagrass/auditor.py
seagrass/base.py
seagrass/errors.py
seagrass/py.typed
seagrass/events/__init__.py
seagrass/events/contexts.py
seagrass/events/event.py
seagrass/hooks/__init__.py
seagrass/hooks/_utils.py
seagrass/hooks/context_manager_hook.py
seagrass/hooks/counter_hook.py
seagrass/hooks/file_open_hook.py
seagrass/hooks/logging_hook.py
seagrass/hooks/profiler_hook.py
seagrass/hooks/runtime_audit_hook.py
seagrass/hooks/stack_trace_hook.py
seagrass/hooks/timer_hook.py
seagrass/hooks/tracing_hook.py
test/__init__.py
test/test_async.py
test/test_auditor.py
test/test_base.py
test/test_events.py
test/test_logging.py
test/utils.py
test/base/__init__.py
test/base/test_cleanup_hook.py
test/hooks/__init__.py
test/hooks/test_context_manager_hook.py
test/hooks/test_counter_hook.py
test/hooks/test_file_open_hook.py
test/hooks/test_logger_hook.py
test/hooks/test_profiler_hook.py
test/hooks/test_runtime_audit_hook.py
test/hooks/test_stack_trace_hook.py
test/hooks/test_timer_hook.py
test/hooks/test_tracing_hook.py
seagrass-0.10.2.dist-info/LICENSE
seagrass-0.10.2.dist-info/METADATA
seagrass-0.10.2.dist-info/WHEEL
seagrass-0.10.2.dist-info/top_level.txt
seagrass-0.10.2.dist-info/RECORD
