Metadata-Version: 2.1
Name: seagrass
Version: 0.10.2
Summary: Auditing and profiling multi-tool
Home-page: https://github.com/kernelmethod/Seagrass/
Author: kernelmethod
Author-email: 17100608+kernelmethod@users.noreply.github.com
License: BSD
Project-URL: Source Code, https://github.com/kernelmethod/Seagrass
Project-URL: Bug Tracker, https://github.com/kernelmethod/Seagrass/issues
Project-URL: Documentation, https://seagrass.readthedocs.io/en/latest/
Classifier: Topic :: System :: Logging
Classifier: Topic :: System :: Monitoring
Classifier: Programming Language :: Python :: 3.8
Classifier: Programming Language :: Python :: 3.9
Classifier: Programming Language :: Python :: 3.10
Requires-Python: >=3.8.0
License-File: LICENSE
Requires-Dist: python-json-logger (==2.0.4)
